thinkware_file_extractor_xethhung12/__init__.py
thinkware_file_extractor_xethhung12/__main__.py
thinkware_file_extractor_xethhung12/automating.py
thinkware_file_extractor_xethhung12/cut.py
thinkware_file_extractor_xethhung12/moving_detector.py
thinkware_file_extractor_xethhung12/script_gen.py
thinkware_file_extractor_xethhung12/utils_tools.py
thinkware_file_extractor_xethhung12/video_clipping.py
thinkware_file_extractor_xethhung12-0.1.17.dist-info/LICENSE
thinkware_file_extractor_xethhung12-0.1.17.dist-info/METADATA
thinkware_file_extractor_xethhung12-0.1.17.dist-info/WHEEL
thinkware_file_extractor_xethhung12-0.1.17.dist-info/top_level.txt
thinkware_file_extractor_xethhung12-0.1.17.dist-info/RECORD
