Metadata-Version: 2.1
Name: thinkware_file_extractor_xethhung12
Version: 0.1.17
Summary: A small example package
Author-email: Xeth <admin@xethh.me>
Project-URL: Homepage, https://github.com/xh-dev/thinkware-file-extractor-xethhung12
Project-URL: Issues, https://github.com/xh-dev/thinkware-file-extractor-xethhung12/issues
Classifier: Programming Language :: Python :: 3
Classifier: License :: OSI Approved :: MIT License
Classifier: Operating System :: OS Independent
Requires-Python: >=3.8
License-File: LICENSE
Requires-Dist: google-api-python-client
Requires-Dist: oauth2client
Requires-Dist: pyyaml
Requires-Dist: opencv-python
Requires-Dist: pytesseract
